[
    "{\"UserID\":\"userID\",\"Sentence\":\"tui \u1edf g\u1ea7n \u0111\u00e2y n\u00e8. b\u00ean l\u00e0ng xe 4 b\u00e1nh kh\u00f4ng ai cho xe 2 b\u00e1nh qua \u0111\u00e2u nha.tr\u1eeb khi \u0111i b\u1ed9 .d\u00e2n \u1edf \u0111\u00e2y nh\u00ecn l\u00e0 hi\u1ec3u\",\"prediction\":0.0,\"Sentence\":\"tui \u1edf g\u1ea7n \u0111\u00e2y n\u00e8. b\u00ean l\u00e0ng xe 4 b\u00e1nh kh\u00f4ng ai cho xe 2 b\u00e1nh qua \u0111\u00e2u nha.tr\u1eeb khi \u0111i b\u1ed9 .d\u00e2n \u1edf \u0111\u00e2y nh\u00ecn l\u00e0 hi\u1ec3u\",\"prediction\":0.0}",
    "{\"UserID\":\"userID\",\"Sentence\":\"r\u1ed3i l\u1ea5y c\u00e1i l\u00ed do g\u00ec \u0111\u1ec3 \u0111c \u01b0u ti\u00ean. v\u1eady?\",\"prediction\":2.0,\"Sentence\":\"r\u1ed3i l\u1ea5y c\u00e1i l\u00ed do g\u00ec \u0111\u1ec3 \u0111c \u01b0u ti\u00ean. v\u1eady?\",\"prediction\":2.0}",
    "{\"UserID\":\"userID\",\"Sentence\":\"N\u00f3 gi\u01a1 tay ch\u1eb7n l\u1ea1i nh\u01b0ng v\u1eabn c\u1ed1 ch\u1ea1y.\",\"prediction\":0.0,\"Sentence\":\"N\u00f3 gi\u01a1 tay ch\u1eb7n l\u1ea1i nh\u01b0ng v\u1eabn c\u1ed1 ch\u1ea1y.\",\"prediction\":0.0}",
    "{\"UserID\":\"userID\",\"Sentence\":\"C\u1ee9 t\u00ednh theo xe oto l\u00e0 xong c\u00e3i nhau l\u00e0m j\",\"prediction\":0.0,\"Sentence\":\"C\u1ee9 t\u00ednh theo xe oto l\u00e0 xong c\u00e3i nhau l\u00e0m j\",\"prediction\":0.0}",
    "{\"UserID\":\"userID\",\"Sentence\":\"b\u1eadt \u01b0u ti\u00ean lun ch\u1ee9,h\u1ea3o h\u00e1n\",\"prediction\":2.0,\"Sentence\":\"b\u1eadt \u01b0u ti\u00ean lun ch\u1ee9,h\u1ea3o h\u00e1n\",\"prediction\":2.0}",
    "{\"UserID\":\"userID\",\"Sentence\":\"\u0110i moto l\u00e0 cha l\u00e0 \u00f4ng n\u1ed9i \ud83d\ude02\ud83d\ude02\ud83d\ude02\",\"prediction\":1.0,\"Sentence\":\"\u0110i moto l\u00e0 cha l\u00e0 \u00f4ng n\u1ed9i \ud83d\ude02\ud83d\ude02\ud83d\ude02\",\"prediction\":1.0}",
    "{\"UserID\":\"userID\",\"Sentence\":\"ph\u00e2n kh\u1ed1i l\u1edbn = kh\u1ed1i ph\u00e2n l\u1edbn\",\"prediction\":2.0,\"Sentence\":\"ph\u00e2n kh\u1ed1i l\u1edbn = kh\u1ed1i ph\u00e2n l\u1edbn\",\"prediction\":2.0}",
    "{\"UserID\":\"userID\",\"Sentence\":\"Xin video l\u00ean u\u1ed1ng n\u01b0\u1edbc c\u00f9ng c\u00f4ng an v\u1edbi \u1ea1\ud83d\ude02\",\"prediction\":0.0,\"Sentence\":\"Xin video l\u00ean u\u1ed1ng n\u01b0\u1edbc c\u00f9ng c\u00f4ng an v\u1edbi \u1ea1\ud83d\ude02\",\"prediction\":0.0}",
    "{\"UserID\":\"userID\",\"Sentence\":\"Kh\u00f4ng ph\u1ea3i ai c\u00f3 ti\u1ec1n c\u0169ng c\u00f3 \u00ed th\u1ee9c\",\"prediction\":0.0,\"Sentence\":\"Kh\u00f4ng ph\u1ea3i ai c\u00f3 ti\u1ec1n c\u0169ng c\u00f3 \u00ed th\u1ee9c\",\"prediction\":0.0}",
    "{\"UserID\":\"userID\",\"Sentence\":\"C\u00f3 th\u1ea5y ai ch\u1eb7n n\u00f3 l\u1ea1i \u0111\u00e2u\",\"prediction\":0.0,\"Sentence\":\"C\u00f3 th\u1ea5y ai ch\u1eb7n n\u00f3 l\u1ea1i \u0111\u00e2u\",\"prediction\":0.0}",
    "{\"UserID\":\"userID\",\"Sentence\":\"ngta ta b\u1eadc \u01b0u ti\u00ean r\u1ed3i k\u00eca.\u0111\u01b0\u1eddg c\u1ee7a \u00f4g c\u1ed1 n\u1ed9i ngta \u0111\u1ec3 l\u1ea1i mn ch\u1ea1y s ch\u1ea1y ch\u1ee9 s h\",\"prediction\":0.0,\"Sentence\":\"ngta ta b\u1eadc \u01b0u ti\u00ean r\u1ed3i k\u00eca.\u0111\u01b0\u1eddg c\u1ee7a \u00f4g c\u1ed1 n\u1ed9i ngta \u0111\u1ec3 l\u1ea1i mn ch\u1ea1y s ch\u1ea1y ch\u1ee9 s h\",\"prediction\":0.0}",
    "{\"UserID\":\"userID\",\"Sentence\":\"2 b\u00e1nh mu\u1ed1n l\u00e0m 4 b\u00e1nh ki\u1ec3u nh\u01b0 \u0111ang \u0111i hay ch\u00e2n l\u1ea1i mu\u1ed1n th\u00e0nh 4 ch\u00e2n \u0111\u1ec3 \u0111i \ud83d\ude01\ud83d\ude01\ud83d\ude01\",\"prediction\":0.0,\"Sentence\":\"2 b\u00e1nh mu\u1ed1n l\u00e0m 4 b\u00e1nh ki\u1ec3u nh\u01b0 \u0111ang \u0111i hay ch\u00e2n l\u1ea1i mu\u1ed1n th\u00e0nh 4 ch\u00e2n \u0111\u1ec3 \u0111i \ud83d\ude01\ud83d\ude01\ud83d\ude01\",\"prediction\":0.0}",
    "{\"UserID\":\"userID\",\"Sentence\":\"Nh\u01b0 m\u1eb9 thi\u00ean h\u1ea1\",\"prediction\":0.0,\"Sentence\":\"Nh\u01b0 m\u1eb9 thi\u00ean h\u1ea1\",\"prediction\":0.0}",
    "{\"UserID\":\"userID\",\"Sentence\":\"c\u00f3 ph\u1ea7n \u0111\u00e1nh ko ad\",\"prediction\":0.0,\"Sentence\":\"c\u00f3 ph\u1ea7n \u0111\u00e1nh ko ad\",\"prediction\":0.0}",
    "{\"UserID\":\"userID\",\"Sentence\":\"b\u1ed9 l\u1ea1 l\u1eafm h\u1ea3\",\"prediction\":1.0,\"Sentence\":\"b\u1ed9 l\u1ea1 l\u1eafm h\u1ea3\",\"prediction\":1.0}",
    "{\"UserID\":\"userID\",\"Sentence\":\"pha cho ng\u01b0\u1ee3c chi\u1ec1u chi co xe c\u1ea5p c\u1ee9u m\u1edbi \u0111\u00fang\",\"prediction\":1.0,\"Sentence\":\"pha cho ng\u01b0\u1ee3c chi\u1ec1u chi co xe c\u1ea5p c\u1ee9u m\u1edbi \u0111\u00fang\",\"prediction\":1.0}",
    "{\"UserID\":\"userID\",\"Sentence\":\"viet h\u00e0 v\u00e0 vi\u1ec7t \u00e1 c\u00f3 b\u00e0 con d\u00f2ng h\u1ecd kh\u00f4ng\",\"prediction\":0.0,\"Sentence\":\"viet h\u00e0 v\u00e0 vi\u1ec7t \u00e1 c\u00f3 b\u00e0 con d\u00f2ng h\u1ecd kh\u00f4ng\",\"prediction\":0.0}",
    "{\"UserID\":\"userID\",\"Sentence\":\"\u0102n no r\u1ed3i m\u1edbi b\u1eaft\",\"prediction\":0.0,\"Sentence\":\"\u0102n no r\u1ed3i m\u1edbi b\u1eaft\",\"prediction\":0.0}",
    "{\"UserID\":\"userID\",\"Sentence\":\"v\u1ec1 \u0111\u1ebfn vn x4 l\u1ea7n.con m\u1eb9 vi\u1ec7t nam t\u00ednh ra t\u00e0i s\u1ea3n c\u00e1 nh\u00e2n ch\u1eafc l\u1edbn nh\u1ea5t tg \u1ea5y ch\u1ee9 m\u00e0 \u0111\u1ed3ng ti\u1ec1n vi\u1ec7t nam nh\u1ecf nh\u01b0 v\u1eady.qu\u00e1 kinh kh\u1ee7ng\",\"prediction\":0.0,\"Sentence\":\"v\u1ec1 \u0111\u1ebfn vn x4 l\u1ea7n.con m\u1eb9 vi\u1ec7t nam t\u00ednh ra t\u00e0i s\u1ea3n c\u00e1 nh\u00e2n ch\u1eafc l\u1edbn nh\u1ea5t tg \u1ea5y ch\u1ee9 m\u00e0 \u0111\u1ed3ng ti\u1ec1n vi\u1ec7t nam nh\u1ecf nh\u01b0 v\u1eady.qu\u00e1 kinh kh\u1ee7ng\",\"prediction\":0.0}",
    "{\"UserID\":\"userID\",\"Sentence\":\"anh \u01a1i em tham gia v\u1edbi anh \u01a1i \ud83d\ude18\",\"prediction\":1.0,\"Sentence\":\"anh \u01a1i em tham gia v\u1edbi anh \u01a1i \ud83d\ude18\",\"prediction\":1.0}",
    "{\"UserID\":\"userID\",\"Sentence\":\"Phi th\u1eb3ng cho Grap Ph\u00e1t\",\"prediction\":0.0,\"Sentence\":\"Phi th\u1eb3ng cho Grap Ph\u00e1t\",\"prediction\":0.0}",
    "{\"UserID\":\"userID\",\"Sentence\":\"\u0110ang ch\u1edd t\u1edbi l\u01b0\u1ee3t t\u1ee5i ngh\u1ec7 s\u0129 v\u00e0 th\u1ebf l\u1ef1c ch\u1ed1ng l\u01b0ng.\",\"prediction\":2.0,\"Sentence\":\"\u0110ang ch\u1edd t\u1edbi l\u01b0\u1ee3t t\u1ee5i ngh\u1ec7 s\u0129 v\u00e0 th\u1ebf l\u1ef1c ch\u1ed1ng l\u01b0ng.\",\"prediction\":2.0}",
    "{\"UserID\":\"userID\",\"Sentence\":\"r\u1eeda ti\u1ec1n c\u1ee7a b\u1ecdn quan tham\",\"prediction\":0.0,\"Sentence\":\"r\u1eeda ti\u1ec1n c\u1ee7a b\u1ecdn quan tham\",\"prediction\":0.0}",
    "{\"UserID\":\"userID\",\"Sentence\":\"n\u1ebfu si\u00eau xe c\u1ee7a th\u1eb1ng Khanh th\u1eadt.th\u00ec Ba M\u1eb9 n\u00f3 \u1edf ch\u1ee3 T\u00e2n H\u00e0o.gi\u1ed3ng Tr\u00f4m.B\u1ebfn Tre.\u0111\u00e2u c\u00f3 b\u01b0ng t\u1eebng t\u00f4 h\u1eefu ti\u1ebfu b\u00e1n \u0111\u1ec3 tran t\u1ea3i cu\u1ed9c s\u1ed1ng h\u00e0ng ng\u00e0y.\",\"prediction\":1.0,\"Sentence\":\"n\u1ebfu si\u00eau xe c\u1ee7a th\u1eb1ng Khanh th\u1eadt.th\u00ec Ba M\u1eb9 n\u00f3 \u1edf ch\u1ee3 T\u00e2n H\u00e0o.gi\u1ed3ng Tr\u00f4m.B\u1ebfn Tre.\u0111\u00e2u c\u00f3 b\u01b0ng t\u1eebng t\u00f4 h\u1eefu ti\u1ebfu b\u00e1n \u0111\u1ec3 tran t\u1ea3i cu\u1ed9c s\u1ed1ng h\u00e0ng ng\u00e0y.\",\"prediction\":1.0}",
    "{\"UserID\":\"userID\",\"Sentence\":\"t\u00f4i ca\u0303i nhau vs bo\u0323n na\u0300y 1 l\u00e2\u0300n r\u00f4\u0300i.no\u0301 ko \u0111\u01a1\u0301p dk no\u0301 nha\u0309 ae a\u0300\",\"prediction\":1.0,\"Sentence\":\"t\u00f4i ca\u0303i nhau vs bo\u0323n na\u0300y 1 l\u00e2\u0300n r\u00f4\u0300i.no\u0301 ko \u0111\u01a1\u0301p dk no\u0301 nha\u0309 ae a\u0300\",\"prediction\":1.0}",
    "{\"UserID\":\"userID\",\"Sentence\":\"b\u1ea1n n\u00f3i sao.se vin l\u00e0m sao ch\u1ebft m\u00e1y \u0111\u01b0\u1ee3c. h\u00e0ng Vi\u1ec7t Nam ch\u1ea5t l\u01b0\u1ee3ng v\u01b0\u01a1n ra th\u1ebf gi\u1edbi\",\"prediction\":1.0,\"Sentence\":\"b\u1ea1n n\u00f3i sao.se vin l\u00e0m sao ch\u1ebft m\u00e1y \u0111\u01b0\u1ee3c. h\u00e0ng Vi\u1ec7t Nam ch\u1ea5t l\u01b0\u1ee3ng v\u01b0\u01a1n ra th\u1ebf gi\u1edbi\",\"prediction\":1.0}",
    "{\"UserID\":\"userID\",\"Sentence\":\"m\u1ea5y b\u00e1c c\u1ee9 b\u1ea3o xe n\u00e0o ko n\u1eb1m \u0111\u01b0\u1eddng. nh\u01b0ng ko c\u00f3 c\u00e1i h\u00e3ng n\u00e0o xe m\u1edbi m\u00e0 n\u1eb1m \u0111\u01b0\u1eddng nhi\u1ec1u nh\u01b0 VinFast h\u1ebft.h\u00e3y c\u00f4ng nh\u1eadn \u0111\u00f3 l\u00e0 l\u1ed7i \u0111\u1ec3 kh\u1eafc ph\u1ee5c.\",\"prediction\":2.0,\"Sentence\":\"m\u1ea5y b\u00e1c c\u1ee9 b\u1ea3o xe n\u00e0o ko n\u1eb1m \u0111\u01b0\u1eddng. nh\u01b0ng ko c\u00f3 c\u00e1i h\u00e3ng n\u00e0o xe m\u1edbi m\u00e0 n\u1eb1m \u0111\u01b0\u1eddng nhi\u1ec1u nh\u01b0 VinFast h\u1ebft.h\u00e3y c\u00f4ng nh\u1eadn \u0111\u00f3 l\u00e0 l\u1ed7i \u0111\u1ec3 kh\u1eafc ph\u1ee5c.\",\"prediction\":2.0}",
    "{\"UserID\":\"userID\",\"Sentence\":\"E \u0111i qua bao l\u1ea7n c\u00f3 th\u1eaft d\u00e2y \u0111\u00e2u m\u00e0 k th\u1ea5y b\u1eaft\ud83d\ude02\ud83d\ude02\",\"prediction\":0.0,\"Sentence\":\"E \u0111i qua bao l\u1ea7n c\u00f3 th\u1eaft d\u00e2y \u0111\u00e2u m\u00e0 k th\u1ea5y b\u1eaft\ud83d\ude02\ud83d\ude02\",\"prediction\":0.0}",
    "{\"UserID\":\"userID\",\"Sentence\":\"M\u1eb7t grab gian th\u1ebf\ud83d\ude02\ud83d\ude02\",\"prediction\":0.0,\"Sentence\":\"M\u1eb7t grab gian th\u1ebf\ud83d\ude02\ud83d\ude02\",\"prediction\":0.0}",
    "{\"UserID\":\"userID\",\"Sentence\":\"xe n\u00f3 \u1edf c\u00e1i t\u1ea7m : t\u1ea7m c\u00f9i b\u1eafp \ud83d\ude02\ud83d\ude02\",\"prediction\":0.0,\"Sentence\":\"xe n\u00f3 \u1edf c\u00e1i t\u1ea7m : t\u1ea7m c\u00f9i b\u1eafp \ud83d\ude02\ud83d\ude02\",\"prediction\":0.0}",
    "{\"UserID\":\"userID\",\"Sentence\":\"Ch\u1eafc l\u1ea1i do phe \u0111\u1ed1i l\u1eadp gi\u00e0n d\u1ef1ng \u0111\u00f3 - Vin N\u00f4 cho hay.\",\"prediction\":2.0,\"Sentence\":\"Ch\u1eafc l\u1ea1i do phe \u0111\u1ed1i l\u1eadp gi\u00e0n d\u1ef1ng \u0111\u00f3 - Vin N\u00f4 cho hay.\",\"prediction\":2.0}",
    "{\"UserID\":\"userID\",\"Sentence\":\"Vin v\u01b0\u1ee3t qua tesla \u0111\u1ee9ng \u0111\u01b0\u1eddng nhi\u1ec1u\",\"prediction\":0.0,\"Sentence\":\"Vin v\u01b0\u1ee3t qua tesla \u0111\u1ee9ng \u0111\u01b0\u1eddng nhi\u1ec1u\",\"prediction\":0.0}",
    "{\"UserID\":\"userID\",\"Sentence\":\"Xe th\u00ec \u0111\u1eb9p n\u00f3i k ph\u1ea3i ch\u00ea nh\u01b0ng m\u00e0 th\u1ea5y l\u1ed7i qu\u00e1 nhi\u1ec1u\",\"prediction\":0.0,\"Sentence\":\"Xe th\u00ec \u0111\u1eb9p n\u00f3i k ph\u1ea3i ch\u00ea nh\u01b0ng m\u00e0 th\u1ea5y l\u1ed7i qu\u00e1 nhi\u1ec1u\",\"prediction\":0.0}",
    "{\"UserID\":\"userID\",\"Sentence\":\"kh\u00f3a 10,kh\u00f3a 10,kh\u00f3a 10,c\u00e2u th\u1ea7n ch\u00fa kh\u00f3a 10\ud83d\ude01\",\"prediction\":1.0,\"Sentence\":\"kh\u00f3a 10,kh\u00f3a 10,kh\u00f3a 10,c\u00e2u th\u1ea7n ch\u00fa kh\u00f3a 10\ud83d\ude01\",\"prediction\":1.0}",
    "{\"UserID\":\"userID\",\"Sentence\":\"t\u1ef1 h\u00e0o l\u1eafm VN.. \ud83d\ude05\ud83d\ude05\",\"prediction\":1.0,\"Sentence\":\"t\u1ef1 h\u00e0o l\u1eafm VN.. \ud83d\ude05\ud83d\ude05\",\"prediction\":1.0}",
    "{\"UserID\":\"userID\",\"Sentence\":\"To\u00e0n n\u1eb1m gi\u1eefa \u0111\u01b0\u1eddng th\u1ebf n\u00e0y nguy hi\u1ec3m qu\u00e1. \ud83d\ude2b\",\"prediction\":0.0,\"Sentence\":\"To\u00e0n n\u1eb1m gi\u1eefa \u0111\u01b0\u1eddng th\u1ebf n\u00e0y nguy hi\u1ec3m qu\u00e1. \ud83d\ude2b\",\"prediction\":0.0}",
    "{\"UserID\":\"userID\",\"Sentence\":\"S\u1eafp t\u1edbi ngh\u1ec1 c\u1ee9u h\u1ed9 oto \u0111i\u1ec7n s\u1ebd r\u1ea5t h\u00f3t\",\"prediction\":2.0,\"Sentence\":\"S\u1eafp t\u1edbi ngh\u1ec1 c\u1ee9u h\u1ed9 oto \u0111i\u1ec7n s\u1ebd r\u1ea5t h\u00f3t\",\"prediction\":2.0}",
    "{\"UserID\":\"userID\",\"Sentence\":\"B\u1edfi v\u1eady l\u0169 Vin n\u00f4 ch\u1ec9 gi\u1ecfi di\u1ec5n k\u1ecbch h\u00f4 h\u00e0o l\u1eeba ng\u01b0\u1eddi kh\u00e1c mua th\u00f4i, c\u00f2n b\u1ea3n th\u00e2n ch\u00fang n\u00f3 th\u00ec t\u00ecm mua xe Nh\u1eadt, H\u00e0n c\u0169 \u0111\u1ec3 \u0111i cho ch\u1eafc \u0103n.\",\"prediction\":1.0,\"Sentence\":\"B\u1edfi v\u1eady l\u0169 Vin n\u00f4 ch\u1ec9 gi\u1ecfi di\u1ec5n k\u1ecbch h\u00f4 h\u00e0o l\u1eeba ng\u01b0\u1eddi kh\u00e1c mua th\u00f4i, c\u00f2n b\u1ea3n th\u00e2n ch\u00fang n\u00f3 th\u00ec t\u00ecm mua xe Nh\u1eadt, H\u00e0n c\u0169 \u0111\u1ec3 \u0111i cho ch\u1eafc \u0103n.\",\"prediction\":1.0}",
    "{\"UserID\":\"userID\",\"Sentence\":\"\u0111i xe h\u00e0n m\u01b0\u1eddi m\u1ea5y n\u0103m ch\u1ea3 th\u1ea5y b\u1ecb j.ch\u1ea3 bao gi\u1edd ph\u1ea3i n\u1eb1m gi\u1eefa \u0111\u01b0\u1eddng ki\u1ec3u n\u00e0y.\",\"prediction\":2.0,\"Sentence\":\"\u0111i xe h\u00e0n m\u01b0\u1eddi m\u1ea5y n\u0103m ch\u1ea3 th\u1ea5y b\u1ecb j.ch\u1ea3 bao gi\u1edd ph\u1ea3i n\u1eb1m gi\u1eefa \u0111\u01b0\u1eddng ki\u1ec3u n\u00e0y.\",\"prediction\":2.0}",
    "{\"UserID\":\"userID\",\"Sentence\":\"kakaka con n\u00e0o ch\u1ea3 b\u1ecb, nhi\u1ec1u ng\u01b0\u1eddi v\u1eabn u m\u00ea l\u1eafm\ud83d\ude02\ud83d\ude02\ud83d\ude02\ud83d\ude02\",\"prediction\":0.0,\"Sentence\":\"kakaka con n\u00e0o ch\u1ea3 b\u1ecb, nhi\u1ec1u ng\u01b0\u1eddi v\u1eabn u m\u00ea l\u1eafm\ud83d\ude02\ud83d\ude02\ud83d\ude02\ud83d\ude02\",\"prediction\":0.0}",
    "{\"UserID\":\"userID\",\"Sentence\":\"M\u1ed9t s\u1ea3n ph\u1ea9m m\u1edbi s\u1ebd c\u1ea7n th\u1eddi gian \u0111\u1ec3 ho\u00e0n thi\u1ec7n h\u01a1n nh\u01b0ng xe \u0111i\u1ec7n l\u00e0 xu th\u1ebf r\u1ed3i.\",\"prediction\":2.0,\"Sentence\":\"M\u1ed9t s\u1ea3n ph\u1ea9m m\u1edbi s\u1ebd c\u1ea7n th\u1eddi gian \u0111\u1ec3 ho\u00e0n thi\u1ec7n h\u01a1n nh\u01b0ng xe \u0111i\u1ec7n l\u00e0 xu th\u1ebf r\u1ed3i.\",\"prediction\":2.0}",
    "{\"UserID\":\"userID\",\"Sentence\":\"kh\u1ed5 th\u1eadt, mua c\u00e1i xe \u0111i cho s\u01b0\u1edbng m\u00e0 l\u1ea1i kh\u1ed5\",\"prediction\":0.0,\"Sentence\":\"kh\u1ed5 th\u1eadt, mua c\u00e1i xe \u0111i cho s\u01b0\u1edbng m\u00e0 l\u1ea1i kh\u1ed5\",\"prediction\":0.0}",
    "{\"UserID\":\"userID\",\"Sentence\":\"\u09b8\u09a4\u09cd\u09af\u09bf \u09a4\u09c1\u09ae\u09bf \u0985\u09a8\u09c7\u0995 \u09b8\u09c1\u09a8\u09cd\u09a6\u09b0 \ud83e\udd70\ud83e\udd70\ud83e\udd70\",\"prediction\":0.0,\"Sentence\":\"\u09b8\u09a4\u09cd\u09af\u09bf \u09a4\u09c1\u09ae\u09bf \u0985\u09a8\u09c7\u0995 \u09b8\u09c1\u09a8\u09cd\u09a6\u09b0 \ud83e\udd70\ud83e\udd70\ud83e\udd70\",\"prediction\":0.0}",
    "{\"UserID\":\"userID\",\"Sentence\":\"nice \ud83d\ude0d\ud83d\ude0d\ud83d\ude0d\",\"prediction\":1.0,\"Sentence\":\"nice \ud83d\ude0d\ud83d\ude0d\ud83d\ude0d\",\"prediction\":1.0}",
    "{\"UserID\":\"userID\",\"Sentence\":\"bwm, mec, volvo.....kia, hyundai c\u00f3 th\u1ec3 s\u1ebd n\u1eb1m \u0111\u01b0\u1eddng nh\u01b0ng t\u1ec9 l\u1ec7 \u00edt. ch\u1ee9 vin F34 hay F8 xe m\u1edbi toanh m\u00e0 th\u1ea5y n\u1eb1m su\u1ed1t\",\"prediction\":1.0,\"Sentence\":\"bwm, mec, volvo.....kia, hyundai c\u00f3 th\u1ec3 s\u1ebd n\u1eb1m \u0111\u01b0\u1eddng nh\u01b0ng t\u1ec9 l\u1ec7 \u00edt. ch\u1ee9 vin F34 hay F8 xe m\u1edbi toanh m\u00e0 th\u1ea5y n\u1eb1m su\u1ed1t\",\"prediction\":1.0}",
    "{\"UserID\":\"userID\",\"Sentence\":\"Nice \ud83e\udd70\",\"prediction\":0.0,\"Sentence\":\"Nice \ud83e\udd70\",\"prediction\":0.0}",
    "{\"UserID\":\"userID\",\"Sentence\":\"vf ch\u1ec9 y\u00eau ti\u1ec1n c\u1ee7a b\u1ea1n, c\u00f2n b\u1ea1n c\u00f3 y\u00eau n\u01b0\u1edbc hay k th\u00ec t\u00f9y b\u1ea1n\",\"prediction\":0.0,\"Sentence\":\"vf ch\u1ec9 y\u00eau ti\u1ec1n c\u1ee7a b\u1ea1n, c\u00f2n b\u1ea1n c\u00f3 y\u00eau n\u01b0\u1edbc hay k th\u00ec t\u00f9y b\u1ea1n\",\"prediction\":0.0}",
    "{\"UserID\":\"userID\",\"Sentence\":\"nice\ud83e\udd70\ud83e\udd70\",\"prediction\":0.0,\"Sentence\":\"nice\ud83e\udd70\ud83e\udd70\",\"prediction\":0.0}",
    "{\"UserID\":\"userID\",\"Sentence\":\"HO\u00e0ng sa - tr\u01b0\u1eddng sa b\u00e1n r\u1ed3i \u00e0 b\",\"prediction\":0.0,\"Sentence\":\"HO\u00e0ng sa - tr\u01b0\u1eddng sa b\u00e1n r\u1ed3i \u00e0 b\",\"prediction\":0.0}",
    "{\"UserID\":\"userID\",\"Sentence\":\"nghe m\u1ea5y th\u1eb1ng v\u1edb v\u1ea9n tin mua xe l\u00e0 c\u1ee9 ch\u1ecbu kh\u00f3 g\u1ecdi c\u1ee9u h\u1ed9\",\"prediction\":0.0,\"Sentence\":\"nghe m\u1ea5y th\u1eb1ng v\u1edb v\u1ea9n tin mua xe l\u00e0 c\u1ee9 ch\u1ecbu kh\u00f3 g\u1ecdi c\u1ee9u h\u1ed9\",\"prediction\":0.0}",
    "{\"UserID\":\"userID\",\"Sentence\":\"kk\",\"prediction\":1.0,\"Sentence\":\"kk\",\"prediction\":1.0}",
    "{\"UserID\":\"userID\",\"Sentence\":\"\ud83e\udd70\ud83e\udd70\ud83e\udd70\ud83e\udd70\",\"prediction\":0.0,\"Sentence\":\"\ud83e\udd70\ud83e\udd70\ud83e\udd70\ud83e\udd70\",\"prediction\":0.0}",
    "{\"UserID\":\"userID\",\"Sentence\":\"\ud83e\udd70\ud83e\udd70\ud83e\udd70\ud83e\udd70\",\"prediction\":0.0,\"Sentence\":\"\ud83e\udd70\ud83e\udd70\ud83e\udd70\ud83e\udd70\",\"prediction\":0.0}",
    "{\"UserID\":\"userID\",\"Sentence\":\"cu\u1ed9c \u0111\u1ed1i \u0111\u1ea7u gi\u1eefa Vin n\u00f4 v\u00e0 l\u0169 \u0111i xe m\u00e1y, b\u1ecdn taxi truy\u1ec1n th\u1ed1ng v\u00e0 c\u1ea3 l\u0169 3 g\u1eady cay c\u00fa :))\",\"prediction\":1.0,\"Sentence\":\"cu\u1ed9c \u0111\u1ed1i \u0111\u1ea7u gi\u1eefa Vin n\u00f4 v\u00e0 l\u0169 \u0111i xe m\u00e1y, b\u1ecdn taxi truy\u1ec1n th\u1ed1ng v\u00e0 c\u1ea3 l\u0169 3 g\u1eady cay c\u00fa :))\",\"prediction\":1.0}",
    "{\"UserID\":\"userID\",\"Sentence\":\"\ud83e\udd70 c\u1ea3m \u01a1n ban t\u1ed5 ch\u1ee9c, v\u00e0 c\u00e1c th\u00e0nh vi\u00ean, \u0111\u1eb9p l\u1eafm lu\u00f4n, nh\u01b0ng thi\u1ebfu Ho\u00e0ng Sa v\u00e0 Tr\u01b0\u1eddng Sa\",\"prediction\":0.0,\"Sentence\":\"\ud83e\udd70 c\u1ea3m \u01a1n ban t\u1ed5 ch\u1ee9c, v\u00e0 c\u00e1c th\u00e0nh vi\u00ean, \u0111\u1eb9p l\u1eafm lu\u00f4n, nh\u01b0ng thi\u1ebfu Ho\u00e0ng Sa v\u00e0 Tr\u01b0\u1eddng Sa\",\"prediction\":0.0}",
    "{\"UserID\":\"userID\",\"Sentence\":\"\u2705\u2705\u2705\",\"prediction\":0.0,\"Sentence\":\"\u2705\u2705\u2705\",\"prediction\":0.0}",
    "{\"UserID\":\"userID\",\"Sentence\":\"\u2764\u2764\u2764\",\"prediction\":1.0,\"Sentence\":\"\u2764\u2764\u2764\",\"prediction\":1.0}",
    "{\"UserID\":\"userID\",\"Sentence\":\"Nh\u1eefng th\u1eb1ng gi\u00e0u \u00edt th\u1eb1ng k s\u1ed1ng ch\u00f3 m\u00e0 c\u00f3 ti\u1ec1n l\u1eafm\",\"prediction\":0.0,\"Sentence\":\"Nh\u1eefng th\u1eb1ng gi\u00e0u \u00edt th\u1eb1ng k s\u1ed1ng ch\u00f3 m\u00e0 c\u00f3 ti\u1ec1n l\u1eafm\",\"prediction\":0.0}",
    "{\"UserID\":\"userID\",\"Sentence\":\"My real name meaning in Greek and Latin is THE DARKNESS\",\"prediction\":1.0,\"Sentence\":\"My real name meaning in Greek and Latin is THE DARKNESS\",\"prediction\":1.0}",
    "{\"UserID\":\"userID\",\"Sentence\":\"Ch\u01b0a x\u1ebfp xong a \u1ea1\ud83d\ude2c\",\"prediction\":1.0,\"Sentence\":\"Ch\u01b0a x\u1ebfp xong a \u1ea1\ud83d\ude2c\",\"prediction\":1.0}",
    "{\"UserID\":\"userID\",\"Sentence\":\"nice\",\"prediction\":0.0,\"Sentence\":\"nice\",\"prediction\":0.0}",
    "{\"UserID\":\"userID\",\"Sentence\":\"wow \ud83e\udd70\ud83e\udd70\ud83e\udd70\",\"prediction\":0.0,\"Sentence\":\"wow \ud83e\udd70\ud83e\udd70\ud83e\udd70\",\"prediction\":0.0}",
    "{\"UserID\":\"userID\",\"Sentence\":\"\ud83e\udd70\ud83e\udd70\ud83e\udd70\",\"prediction\":1.0,\"Sentence\":\"\ud83e\udd70\ud83e\udd70\ud83e\udd70\",\"prediction\":1.0}",
    "{\"UserID\":\"userID\",\"Sentence\":\"\ud83d\ude33\ud83d\ude33\ud83d\ude33q\",\"prediction\":0.0,\"Sentence\":\"\ud83d\ude33\ud83d\ude33\ud83d\ude33q\",\"prediction\":0.0}",
    "{\"UserID\":\"userID\",\"Sentence\":\"\ud83d\ude02\ud83d\ude02 Kh\u1ed5... T\u1ed5 ch\u1ee9c gi\u1ea3i xong l\u1ed9 \u0111ang n\u1ee3\",\"prediction\":0.0,\"Sentence\":\"\ud83d\ude02\ud83d\ude02 Kh\u1ed5... T\u1ed5 ch\u1ee9c gi\u1ea3i xong l\u1ed9 \u0111ang n\u1ee3\",\"prediction\":0.0}",
    "{\"UserID\":\"userID\",\"Sentence\":\"chua \u0111\u1ee7 c\u01a1 s\u1edf \u0111\u1ec3 truy t\u1ed1 \ud83d\ude02\ud83d\ude02\ud83d\ude02\ud83d\ude02\",\"prediction\":1.0,\"Sentence\":\"chua \u0111\u1ee7 c\u01a1 s\u1edf \u0111\u1ec3 truy t\u1ed1 \ud83d\ude02\ud83d\ude02\ud83d\ude02\ud83d\ude02\",\"prediction\":1.0}",
    "{\"UserID\":\"userID\",\"Sentence\":\"\ud83e\udd70\ud83e\udd70\ud83e\udd70\",\"prediction\":1.0,\"Sentence\":\"\ud83e\udd70\ud83e\udd70\ud83e\udd70\",\"prediction\":1.0}",
    "{\"UserID\":\"userID\",\"Sentence\":\"\ud83e\udd70\ud83e\udd70\ud83e\udd70\",\"prediction\":1.0,\"Sentence\":\"\ud83e\udd70\ud83e\udd70\ud83e\udd70\",\"prediction\":1.0}",
    "{\"UserID\":\"userID\",\"Sentence\":\"wow\",\"prediction\":0.0,\"Sentence\":\"wow\",\"prediction\":0.0}",
    "{\"UserID\":\"userID\",\"Sentence\":\"\ud83e\udd70\ud83e\udd70\ud83e\udd70\",\"prediction\":1.0,\"Sentence\":\"\ud83e\udd70\ud83e\udd70\ud83e\udd70\",\"prediction\":1.0}",
    "{\"UserID\":\"userID\",\"Sentence\":\"\ud83e\udd70\ud83e\udd70\",\"prediction\":1.0,\"Sentence\":\"\ud83e\udd70\ud83e\udd70\",\"prediction\":1.0}",
    "{\"UserID\":\"userID\",\"Sentence\":\"wow\",\"prediction\":0.0,\"Sentence\":\"wow\",\"prediction\":0.0}",
    "{\"UserID\":\"userID\",\"Sentence\":\"C\u00f9ng nh\u00e0 xe \u0111\u1ea5y\",\"prediction\":0.0,\"Sentence\":\"C\u00f9ng nh\u00e0 xe \u0111\u1ea5y\",\"prediction\":0.0}",
    "{\"UserID\":\"userID\",\"Sentence\":\"doanh nghi\u1ec7p n\u00e0y ch\u1eafc th\u1ee9 d\u1eef kh\u00f4ng th\u00ec s\u1ebd kh\u00f4ng d\u00e1m!\",\"prediction\":0.0,\"Sentence\":\"doanh nghi\u1ec7p n\u00e0y ch\u1eafc th\u1ee9 d\u1eef kh\u00f4ng th\u00ec s\u1ebd kh\u00f4ng d\u00e1m!\",\"prediction\":0.0}",
    "{\"UserID\":\"userID\",\"Sentence\":\"Kh\u00f4ng th\u1ec3 ch\u1ea5p nh\u1eadn \u0111\u01b0\u1ee3c\",\"prediction\":0.0,\"Sentence\":\"Kh\u00f4ng th\u1ec3 ch\u1ea5p nh\u1eadn \u0111\u01b0\u1ee3c\",\"prediction\":0.0}",
    "{\"UserID\":\"userID\",\"Sentence\":\"an t\u00e2m lu\u1eadt ph\u00e1p nh\u00e2n \u0111\u1ea1o l\u1eafm\",\"prediction\":0.0,\"Sentence\":\"an t\u00e2m lu\u1eadt ph\u00e1p nh\u00e2n \u0111\u1ea1o l\u1eafm\",\"prediction\":0.0}",
    "{\"UserID\":\"userID\",\"Sentence\":\"wow\",\"prediction\":0.0,\"Sentence\":\"wow\",\"prediction\":0.0}",
    "{\"UserID\":\"userID\",\"Sentence\":\"T\u01b0\u1edbc b\u1eb1ng V\u0129nh vi\u1ec5n\",\"prediction\":0.0,\"Sentence\":\"T\u01b0\u1edbc b\u1eb1ng V\u0129nh vi\u1ec5n\",\"prediction\":0.0}",
    "{\"UserID\":\"userID\",\"Sentence\":\"po tay\",\"prediction\":0.0,\"Sentence\":\"po tay\",\"prediction\":0.0}",
    "{\"UserID\":\"userID\",\"Sentence\":\"l\u00e1i xe t\u1ea3i \u0111a s\u1ed1 x\u00fat d\u1eb7c\",\"prediction\":0.0,\"Sentence\":\"l\u00e1i xe t\u1ea3i \u0111a s\u1ed1 x\u00fat d\u1eb7c\",\"prediction\":0.0}",
    "{\"UserID\":\"userID\",\"Sentence\":\"T\u01b0\u1edbc b\u1eb1ng v\u0129nh vi\u1ec5n\",\"prediction\":0.0,\"Sentence\":\"T\u01b0\u1edbc b\u1eb1ng v\u0129nh vi\u1ec5n\",\"prediction\":0.0}",
    "{\"UserID\":\"userID\",\"Sentence\":\"B\u1ecdn xe t\u1ea3i to\u00e0n \u0111i l\u00e0m\",\"prediction\":0.0,\"Sentence\":\"B\u1ecdn xe t\u1ea3i to\u00e0n \u0111i l\u00e0m\",\"prediction\":0.0}",
    "{\"UserID\":\"userID\",\"Sentence\":\"ae ai c\u0169ng bik l\u00e1i xe cho h\u1ecfi l\u00fd do g\u00ec m\u00e0 th\u1eb1ng xe c\u00f4ng b\u00ean tr\u00e1i n\u00f3 \u0111i ch\u1eadm sao ko ch\u1ecbu nh\u1eadp l\u00e0n b\u00ean ph\u1ea3i v\u1eady m\u1ecdi ng\u01b0\u1eddi\",\"prediction\":2.0,\"Sentence\":\"ae ai c\u0169ng bik l\u00e1i xe cho h\u1ecfi l\u00fd do g\u00ec m\u00e0 th\u1eb1ng xe c\u00f4ng b\u00ean tr\u00e1i n\u00f3 \u0111i ch\u1eadm sao ko ch\u1ecbu nh\u1eadp l\u00e0n b\u00ean ph\u1ea3i v\u1eady m\u1ecdi ng\u01b0\u1eddi\",\"prediction\":2.0}",
    "{\"UserID\":\"userID\",\"Sentence\":\"2 xe th\u00ec pat doanh nghi\u1ec7p th\u1eadt n\u1eb7ng v\u00e0 t\u01b0\u1edbc b\u1eb1ng t\u00e0i x\u1ebf v\u0129nh vi\u1ec5n\",\"prediction\":0.0,\"Sentence\":\"2 xe th\u00ec pat doanh nghi\u1ec7p th\u1eadt n\u1eb7ng v\u00e0 t\u01b0\u1edbc b\u1eb1ng t\u00e0i x\u1ebf v\u0129nh vi\u1ec5n\",\"prediction\":0.0}",
    "{\"UserID\":\"userID\",\"Sentence\":\"\ud83d\ude25\ud83d\ude21\",\"prediction\":0.0,\"Sentence\":\"\ud83d\ude25\ud83d\ude21\",\"prediction\":0.0}",
    "{\"UserID\":\"userID\",\"Sentence\":\"t\u01b0\u1edbc b\u1eb1ng\",\"prediction\":0.0,\"Sentence\":\"t\u01b0\u1edbc b\u1eb1ng\",\"prediction\":0.0}",
    "{\"UserID\":\"userID\",\"Sentence\":\"n\u00f3 \u0110ang leo d\u1ed1c c\u1ea7u\",\"prediction\":0.0,\"Sentence\":\"n\u00f3 \u0110ang leo d\u1ed1c c\u1ea7u\",\"prediction\":0.0}",
    "{\"UserID\":\"userID\",\"Sentence\":\"Ad cho em h\u1ecfi con LuxA n\u00e0y th\u1eadt ch\u1ea5t \u0103n bn l\u00edt /100km v\u1eady ak\",\"prediction\":0.0,\"Sentence\":\"Ad cho em h\u1ecfi con LuxA n\u00e0y th\u1eadt ch\u1ea5t \u0103n bn l\u00edt /100km v\u1eady ak\",\"prediction\":0.0}",
    "{\"UserID\":\"userID\",\"Sentence\":\"b\u1ecdn n\u00e0y c\u1ee9 thu b\u1eb1ng vv ko cho ch\u00fang n\u00f3 n\u1ed9ng h\u00e0nh n\u1eefa\",\"prediction\":0.0,\"Sentence\":\"b\u1ecdn n\u00e0y c\u1ee9 thu b\u1eb1ng vv ko cho ch\u00fang n\u00f3 n\u1ed9ng h\u00e0nh n\u1eefa\",\"prediction\":0.0}",
    "{\"UserID\":\"userID\",\"Sentence\":\"\u0110\u1ed9 phong c\u00e1ch c\u1ea3i l\u01b0\u01a1ng nam b\u1ed9 \ud83e\udd23\",\"prediction\":1.0,\"Sentence\":\"\u0110\u1ed9 phong c\u00e1ch c\u1ea3i l\u01b0\u01a1ng nam b\u1ed9 \ud83e\udd23\",\"prediction\":1.0}",
    "{\"UserID\":\"userID\",\"Sentence\":\"\ud83e\udd70\ud83e\udd70\",\"prediction\":1.0,\"Sentence\":\"\ud83e\udd70\ud83e\udd70\",\"prediction\":1.0}",
    "{\"UserID\":\"userID\",\"Sentence\":\"wow\",\"prediction\":0.0,\"Sentence\":\"wow\",\"prediction\":0.0}",
    "{\"UserID\":\"userID\",\"Sentence\":\"\u01b0\u01a1c\",\"prediction\":0.0,\"Sentence\":\"\u01b0\u01a1c\",\"prediction\":0.0}",
    "{\"UserID\":\"userID\",\"Sentence\":\"\u09ad\u09be\u0987\u09df\u09be \u0986\u09aa\u09a8\u09bf \u0995\u09bf \u099c\u09be\u09a8\u09c7\u09a8 \u0986\u09ae\u09be\u09b0 \u0986\u0987\u09a1\u09bf \u099f\u09be \u09ab\u09bf\u0989\u099c \u09b9\u09df\u09c7\u099b\u09c7 \u09b6\u09c7\u09df\u09be\u09b0 \u099a\u09be\u0987\",\"prediction\":1.0,\"Sentence\":\"\u09ad\u09be\u0987\u09df\u09be \u0986\u09aa\u09a8\u09bf \u0995\u09bf \u099c\u09be\u09a8\u09c7\u09a8 \u0986\u09ae\u09be\u09b0 \u0986\u0987\u09a1\u09bf \u099f\u09be \u09ab\u09bf\u0989\u099c \u09b9\u09df\u09c7\u099b\u09c7 \u09b6\u09c7\u09df\u09be\u09b0 \u099a\u09be\u0987\",\"prediction\":1.0}",
    "{\"UserID\":\"userID\",\"Sentence\":\"lux a \u0111\u00e3 \u0111\u1eb9p r\u1ed3i m\u00e0 th\u00eam d\u00e0n \u1ea5y \u0111\u00fang \u0111\u1eb9p X m\u1ea5y l\u1ea7n \ud83d\ude01\",\"prediction\":1.0,\"Sentence\":\"lux a \u0111\u00e3 \u0111\u1eb9p r\u1ed3i m\u00e0 th\u00eam d\u00e0n \u1ea5y \u0111\u00fang \u0111\u1eb9p X m\u1ea5y l\u1ea7n \ud83d\ude01\",\"prediction\":1.0}",
    "{\"UserID\":\"userID\",\"Sentence\":\"\ud83d\ude02\ud83d\ude02\ud83d\ude02\ud83d\ude02\ud83d\ude02\ud83d\ude02\ud83d\ude02\",\"prediction\":0.0,\"Sentence\":\"\ud83d\ude02\ud83d\ude02\ud83d\ude02\ud83d\ude02\ud83d\ude02\ud83d\ude02\ud83d\ude02\",\"prediction\":0.0}",
    "{\"UserID\":\"userID\",\"Sentence\":\"nice\",\"prediction\":0.0,\"Sentence\":\"nice\",\"prediction\":0.0}",
    "{\"UserID\":\"userID\",\"Sentence\":\"may m\u00e0 kh\u00f4ng ph\u1ea3i xe Vin\",\"prediction\":1.0,\"Sentence\":\"may m\u00e0 kh\u00f4ng ph\u1ea3i xe Vin\",\"prediction\":1.0}",
    "{\"UserID\":\"userID\",\"Sentence\":\"Ko ph\u1ea3i xe vin th\u00ec ko hot \ud83d\ude02\ud83d\ude02\ud83d\ude02\",\"prediction\":1.0,\"Sentence\":\"Ko ph\u1ea3i xe vin th\u00ec ko hot \ud83d\ude02\ud83d\ude02\ud83d\ude02\",\"prediction\":1.0}",
    "{\"UserID\":\"userID\",\"Sentence\":\"X\u0103ng d\u1ecfm\",\"prediction\":0.0,\"Sentence\":\"X\u0103ng d\u1ecfm\",\"prediction\":0.0}",
    "{\"UserID\":\"userID\",\"Sentence\":\"\u09a8\u09be\",\"prediction\":0.0,\"Sentence\":\"\u09a8\u09be\",\"prediction\":0.0}",
    "{\"UserID\":\"userID\",\"Sentence\":\"\u0993\u0995\u09c7 \u09ac\u09a8\u09cd\u09a7\u09c1\",\"prediction\":0.0,\"Sentence\":\"\u0993\u0995\u09c7 \u09ac\u09a8\u09cd\u09a7\u09c1\",\"prediction\":0.0}",
    "{\"UserID\":\"userID\",\"Sentence\":\"x\u0103ng \u0111\u1ec3u\",\"prediction\":0.0,\"Sentence\":\"x\u0103ng \u0111\u1ec3u\",\"prediction\":0.0}",
    "{\"UserID\":\"userID\",\"Sentence\":\"Do \u0111\u1ec3 v\u1eadt d\u1ec5 b\u1eaft n\u1eafng trong xe nh\u00e1. Trai n\u01b0\u1edbc hoa. Trai n\u01b0\u1edbc c\u00e1c ki\u1ec3u n\u00ean ch\u00e1y th\u00f4i\",\"prediction\":1.0,\"Sentence\":\"Do \u0111\u1ec3 v\u1eadt d\u1ec5 b\u1eaft n\u1eafng trong xe nh\u00e1. Trai n\u01b0\u1edbc hoa. Trai n\u01b0\u1edbc c\u00e1c ki\u1ec3u n\u00ean ch\u00e1y th\u00f4i\",\"prediction\":1.0}",
    "{\"UserID\":\"userID\",\"Sentence\":\"Kh\u00f4ng s\u1ee3 \u0111\u1ea5y\",\"prediction\":0.0,\"Sentence\":\"Kh\u00f4ng s\u1ee3 \u0111\u1ea5y\",\"prediction\":0.0}",
    "{\"UserID\":\"userID\",\"Sentence\":\"L\u00ean ktra c\u00e1c c\u00e2y x\u0103ng . t\u00f4i c\u00f3 1 ni\u1ec1m tin x\u0103ng gi\u1ea3 vs b\u01a1m thi\u1ebfu ...\",\"prediction\":0.0,\"Sentence\":\"L\u00ean ktra c\u00e1c c\u00e2y x\u0103ng . t\u00f4i c\u00f3 1 ni\u1ec1m tin x\u0103ng gi\u1ea3 vs b\u01a1m thi\u1ebfu ...\",\"prediction\":0.0}",
    "{\"UserID\":\"userID\",\"Sentence\":\"T\u1ea1i \u0111\u0103ng ki\u1ec3m \u1ea9u\",\"prediction\":0.0,\"Sentence\":\"T\u1ea1i \u0111\u0103ng ki\u1ec3m \u1ea9u\",\"prediction\":0.0}"
]